formlayout.py
formlayout-1.2.0.dist-info/LICENSE
formlayout-1.2.0.dist-info/METADATA
formlayout-1.2.0.dist-info/WHEEL
formlayout-1.2.0.dist-info/top_level.txt
formlayout-1.2.0.dist-info/RECORD
