Metadata-Version: 2.1
Name: formlayout
Version: 1.2.0
Summary: The most easy way to create Qt form dialogs and widgets with Python
Home-page: https://github.com/PierreRaybaut/formlayout
Author: Pierre Raybaut
Author-email: pierre.raybaut@gmail.com
License: MIT
Keywords: PyQt4 PyQt5 PySide GUI
Platform: any
Classifier: Development Status :: 5 - Production/Stable
Classifier: License :: OSI Approved :: MIT License
Classifier: Topic :: Software Development :: Widget Sets
Classifier: Operating System :: MacOS
Classifier: Operating System :: Microsoft :: Windows
Classifier: Operating System :: OS Independent
Classifier: Operating System :: POSIX
Classifier: Operating System :: Unix
Classifier: Programming Language :: Python :: 2.7
Classifier: Programming Language :: Python :: 3
